truepy/__init__.py
truepy/__main__.py
truepy/_bean.py
truepy/_bean_serializers.py
truepy/_info.py
truepy/_license.py
truepy/_license_data.py
truepy/_name.py
truepy-2.0.4.dist-info/LICENSE
truepy-2.0.4.dist-info/METADATA
truepy-2.0.4.dist-info/WHEEL
truepy-2.0.4.dist-info/pbr.json
truepy-2.0.4.dist-info/top_level.txt
truepy-2.0.4.dist-info/zip-safe
truepy-2.0.4.dist-info/RECORD
