Metadata-Version: 2.1
Name: truepy
Version: 2.0.4
Summary: A Python library to create TrueLicense license files.
Home-page: https://github.com/moses-palmer/truepy
Author: Moses Palmér
Author-email: moses.palmer@gmail.com
License: GPLv3
Platform: linux
Platform: windows
Requires-Dist: cryptography (>=1.0)
Requires-Dist: pycryptodome (>=3.9.4)
